{"schema_version":"2.0","market":"US","symbol":"TGE-WS","currency":"USD","interval":"1d","provider":"STOOQ","endpoint":"d_us_txt.zip","adjustment_status":"STOOQ_ADJUSTED_OHLC","delayed_or_live":"EOD","fallback_label":"FREE_PRIMARY","data_as_of":"2026-06-18","bars":[{"date":"2025-07-30","open":0.54,"high":0.54,"low":0.54,"close":0.54,"adjusted_close":0.54,"volume":272},{"date":"2025-08-01","open":0.33,"high":0.33,"low":0.32,"close":0.32,"adjusted_close":0.32,"volume":710},{"date":"2025-08-04","open":0.33,"high":0.37,"low":0.3002,"close":0.37,"adjusted_close":0.37,"volume":6700},{"date":"2025-08-05","open":0.47,"high":0.47,"low":0.3002,"close":0.36,"adjusted_close":0.36,"volume":1343},{"date":"2025-08-06","open":0.46,"high":0.46,"low":0.33,"close":0.33,"adjusted_close":0.33,"volume":292},{"date":"2025-08-07","open":0.3001,"high":0.35,"low":0.3,"close":0.32,"adjusted_close":0.32,"volume":3276},{"date":"2025-08-08","open":0.3,"high":0.33,"low":0.29,"close":0.3,"adjusted_close":0.3,"volume":60948},{"date":"2025-08-11","open":0.44,"high":0.44,"low":0.35,"close":0.35,"adjusted_close":0.35,"volume":200},{"date":"2025-08-12","open":0.3,"high":0.43,"low":0.3,"close":0.3,"adjusted_close":0.3,"volume":5592},{"date":"2025-08-13","open":0.3,"high":0.4401,"low":0.3,"close":0.325,"adjusted_close":0.325,"volume":80176},{"date":"2025-08-14","open":0.311,"high":0.33,"low":0.25,"close":0.3,"adjusted_close":0.3,"volume":30086},{"date":"2025-08-15","open":0.44,"high":0.44,"low":0.44,"close":0.44,"adjusted_close":0.44,"volume":150},{"date":"2025-08-18","open":0.3,"high":0.3,"low":0.3,"close":0.3,"adjusted_close":0.3,"volume":2189},{"date":"2025-08-19","open":0.31,"high":0.336,"low":0.3,"close":0.3,"adjusted_close":0.3,"volume":23270},{"date":"2025-08-20","open":0.3,"high":0.31,"low":0.3,"close":0.3,"adjusted_close":0.3,"volume":2967},{"date":"2025-08-21","open":0.31,"high":0.31,"low":0.3,"close":0.3,"adjusted_close":0.3,"volume":2367},{"date":"2025-08-22","open":0.42,"high":0.42,"low":0.28,"close":0.3,"adjusted_close":0.3,"volume":5933},{"date":"2025-08-25","open":0.3,"high":0.3,"low":0.3,"close":0.3,"adjusted_close":0.3,"volume":5230},{"date":"2025-08-26","open":0.3,"high":0.3085,"low":0.2701,"close":0.3,"adjusted_close":0.3,"volume":19661},{"date":"2025-08-27","open":0.3,"high":0.3,"low":0.3,"close":0.3,"adjusted_close":0.3,"volume":2902},{"date":"2025-08-28","open":0.3,"high":0.35,"low":0.3,"close":0.35,"adjusted_close":0.35,"volume":5026},{"date":"2025-08-29","open":0.3,"high":0.3,"low":0.3,"close":0.3,"adjusted_close":0.3,"volume":5000},{"date":"2025-09-02","open":0.3,"high":0.3,"low":0.27,"close":0.2741,"adjusted_close":0.2741,"volume":3190},{"date":"2025-09-03","open":0.3,"high":0.31,"low":0.29,"close":0.3,"adjusted_close":0.3,"volume":3737},{"date":"2025-09-04","open":0.3,"high":0.3001,"low":0.29,"close":0.29,"adjusted_close":0.29,"volume":8339},{"date":"2025-09-05","open":0.3,"high":0.3,"low":0.3,"close":0.3,"adjusted_close":0.3,"volume":4612},{"date":"2025-09-08","open":0.3,"high":0.3,"low":0.29,"close":0.3,"adjusted_close":0.3,"volume":8883},{"date":"2025-09-09","open":0.3,"high":0.33,"low":0.3,"close":0.3,"adjusted_close":0.3,"volume":4729},{"date":"2025-09-10","open":0.3,"high":0.3,"low":0.3,"close":0.3,"adjusted_close":0.3,"volume":1521},{"date":"2025-09-11","open":0.3,"high":0.31,"low":0.29,"close":0.3,"adjusted_close":0.3,"volume":6466},{"date":"2025-09-12","open":0.3,"high":0.3646,"low":0.3,"close":0.31,"adjusted_close":0.31,"volume":6527},{"date":"2025-09-15","open":0.31,"high":0.31,"low":0.3,"close":0.3,"adjusted_close":0.3,"volume":6577},{"date":"2025-09-16","open":0.3,"high":0.31,"low":0.3,"close":0.3,"adjusted_close":0.3,"volume":11588},{"date":"2025-09-17","open":0.3,"high":0.465,"low":0.275,"close":0.275,"adjusted_close":0.275,"volume":62531},{"date":"2025-09-18","open":0.3,"high":0.312,"low":0.275,"close":0.29,"adjusted_close":0.29,"volume":56341},{"date":"2025-09-19","open":0.29,"high":0.29,"low":0.29,"close":0.29,"adjusted_close":0.29,"volume":200},{"date":"2025-09-22","open":0.2701,"high":0.2701,"low":0.19,"close":0.1994,"adjusted_close":0.1994,"volume":23282},{"date":"2025-09-23","open":0.264,"high":0.264,"low":0.25,"close":0.25,"adjusted_close":0.25,"volume":2323},{"date":"2025-09-24","open":0.1901,"high":0.1901,"low":0.19,"close":0.19,"adjusted_close":0.19,"volume":355},{"date":"2025-09-25","open":0.21,"high":0.21,"low":0.21,"close":0.21,"adjusted_close":0.21,"volume":746},{"date":"2025-09-26","open":0.2102,"high":0.2102,"low":0.21,"close":0.21,"adjusted_close":0.21,"volume":5055},{"date":"2025-09-30","open":0.21,"high":0.21,"low":0.13,"close":0.131,"adjusted_close":0.131,"volume":71869},{"date":"2025-10-01","open":0.1321,"high":0.1321,"low":0.11,"close":0.11,"adjusted_close":0.11,"volume":11369},{"date":"2025-10-02","open":0.1102,"high":0.1102,"low":0.09,"close":0.09,"adjusted_close":0.09,"volume":36221},{"date":"2025-10-03","open":0.09,"high":0.0941,"low":0.08,"close":0.08,"adjusted_close":0.08,"volume":46701},{"date":"2025-10-06","open":0.1035,"high":0.127,"low":0.0706,"close":0.072,"adjusted_close":0.072,"volume":41700},{"date":"2025-10-07","open":0.1152,"high":0.12,"low":0.08,"close":0.119,"adjusted_close":0.119,"volume":13182},{"date":"2025-10-08","open":0.1134,"high":0.16,"low":0.08,"close":0.08,"adjusted_close":0.08,"volume":36698},{"date":"2025-10-09","open":0.08,"high":0.0999,"low":0.07,"close":0.08,"adjusted_close":0.08,"volume":12195},{"date":"2025-10-10","open":0.1,"high":0.1,"low":0.08,"close":0.085,"adjusted_close":0.085,"volume":7201},{"date":"2025-10-13","open":0.0703,"high":0.1,"low":0.0703,"close":0.1,"adjusted_close":0.1,"volume":363},{"date":"2025-10-14","open":0.11,"high":0.11,"low":0.0807,"close":0.087,"adjusted_close":0.087,"volume":10998},{"date":"2025-10-16","open":0.09345,"high":0.1049,"low":0.07,"close":0.0964,"adjusted_close":0.0964,"volume":15358},{"date":"2025-10-20","open":0.07,"high":0.1,"low":0.07,"close":0.1,"adjusted_close":0.1,"volume":5043},{"date":"2025-10-21","open":0.0901,"high":0.1,"low":0.08,"close":0.08,"adjusted_close":0.08,"volume":8023},{"date":"2025-10-22","open":0.075,"high":0.1097,"low":0.07,"close":0.07,"adjusted_close":0.07,"volume":8922},{"date":"2025-10-23","open":0.1099,"high":0.1099,"low":0.0614,"close":0.1,"adjusted_close":0.1,"volume":17175},{"date":"2025-10-24","open":0.1,"high":0.11969,"low":0.085,"close":0.11,"adjusted_close":0.11,"volume":2113},{"date":"2025-10-27","open":0.1,"high":0.1,"low":0.1,"close":0.1,"adjusted_close":0.1,"volume":263},{"date":"2025-10-28","open":0.085,"high":0.1099,"low":0.085,"close":0.1098,"adjusted_close":0.1098,"volume":157428},{"date":"2025-10-29","open":0.085,"high":0.1098,"low":0.085,"close":0.1098,"adjusted_close":0.1098,"volume":1300},{"date":"2025-10-30","open":0.0884,"high":0.1099,"low":0.085,"close":0.1099,"adjusted_close":0.1099,"volume":28412},{"date":"2025-10-31","open":0.11295,"high":0.3244,"low":0.101,"close":0.101,"adjusted_close":0.101,"volume":198380},{"date":"2025-11-03","open":0.23,"high":0.25,"low":0.1201,"close":0.2001,"adjusted_close":0.2001,"volume":72878},{"date":"2025-11-04","open":0.2038,"high":0.23,"low":0.16,"close":0.16,"adjusted_close":0.16,"volume":5159},{"date":"2025-11-05","open":0.1576,"high":0.23999,"low":0.1472,"close":0.16,"adjusted_close":0.16,"volume":2992},{"date":"2025-11-06","open":0.2,"high":0.2,"low":0.1401,"close":0.1707,"adjusted_close":0.1707,"volume":2127},{"date":"2025-11-07","open":0.1698,"high":0.2,"low":0.1698,"close":0.1999,"adjusted_close":0.1999,"volume":1178},{"date":"2025-11-10","open":0.19472,"high":0.2398,"low":0.1301,"close":0.2398,"adjusted_close":0.2398,"volume":8949},{"date":"2025-11-11","open":0.2207,"high":0.259899,"low":0.2008,"close":0.25,"adjusted_close":0.25,"volume":3082},{"date":"2025-11-12","open":0.26,"high":0.26,"low":0.1011,"close":0.24,"adjusted_close":0.24,"volume":5351},{"date":"2025-11-13","open":0.23,"high":0.2494,"low":0.1618,"close":0.1618,"adjusted_close":0.1618,"volume":13267},{"date":"2025-11-14","open":0.1905,"high":0.1905,"low":0.1905,"close":0.1905,"adjusted_close":0.1905,"volume":452},{"date":"2025-11-18","open":0.1615,"high":0.2484,"low":0.1011,"close":0.2484,"adjusted_close":0.2484,"volume":3038},{"date":"2025-11-19","open":0.15,"high":0.1896,"low":0.15,"close":0.1896,"adjusted_close":0.1896,"volume":776},{"date":"2025-11-24","open":0.139,"high":0.1964,"low":0.139,"close":0.19,"adjusted_close":0.19,"volume":969},{"date":"2025-11-26","open":0.1751,"high":0.1751,"low":0.1564,"close":0.1667,"adjusted_close":0.1667,"volume":3116},{"date":"2025-11-28","open":0.19,"high":0.1953,"low":0.19,"close":0.1953,"adjusted_close":0.1953,"volume":671},{"date":"2025-12-03","open":0.23,"high":0.23,"low":0.18,"close":0.18,"adjusted_close":0.18,"volume":647},{"date":"2025-12-04","open":0.1556,"high":0.1587,"low":0.1429,"close":0.1429,"adjusted_close":0.1429,"volume":3160},{"date":"2025-12-05","open":0.15,"high":0.1901,"low":0.15,"close":0.180946,"adjusted_close":0.180946,"volume":18745},{"date":"2025-12-09","open":0.15,"high":0.1904,"low":0.1304,"close":0.1904,"adjusted_close":0.1904,"volume":844},{"date":"2025-12-12","open":0.1303,"high":0.1899,"low":0.1303,"close":0.135,"adjusted_close":0.135,"volume":10109},{"date":"2025-12-15","open":0.13,"high":0.19,"low":0.115,"close":0.19,"adjusted_close":0.19,"volume":1649},{"date":"2025-12-16","open":0.19,"high":0.19,"low":0.19,"close":0.19,"adjusted_close":0.19,"volume":121},{"date":"2025-12-19","open":0.159,"high":0.17,"low":0.146,"close":0.1599,"adjusted_close":0.1599,"volume":2575},{"date":"2025-12-24","open":0.137,"high":0.1603,"low":0.137,"close":0.1603,"adjusted_close":0.1603,"volume":1506},{"date":"2025-12-26","open":0.1501,"high":0.2,"low":0.15,"close":0.2,"adjusted_close":0.2,"volume":29405},{"date":"2025-12-29","open":0.15,"high":0.198,"low":0.15,"close":0.19,"adjusted_close":0.19,"volume":2210},{"date":"2025-12-30","open":0.15,"high":0.15,"low":0.15,"close":0.15,"adjusted_close":0.15,"volume":224},{"date":"2025-12-31","open":0.1505,"high":0.1505,"low":0.15,"close":0.15,"adjusted_close":0.15,"volume":12355},{"date":"2026-01-05","open":0.1808,"high":0.2,"low":0.1808,"close":0.2,"adjusted_close":0.2,"volume":626},{"date":"2026-01-06","open":0.1562,"high":0.2,"low":0.1562,"close":0.2,"adjusted_close":0.2,"volume":1070},{"date":"2026-01-08","open":0.1888,"high":0.1888,"low":0.16,"close":0.175,"adjusted_close":0.175,"volume":1318},{"date":"2026-01-09","open":0.156,"high":0.156,"low":0.156,"close":0.156,"adjusted_close":0.156,"volume":441},{"date":"2026-01-12","open":0.2,"high":0.2,"low":0.15,"close":0.1635,"adjusted_close":0.1635,"volume":4724},{"date":"2026-01-13","open":0.1925,"high":0.2,"low":0.1925,"close":0.2,"adjusted_close":0.2,"volume":549},{"date":"2026-01-14","open":0.2,"high":0.2,"low":0.1575,"close":0.1998,"adjusted_close":0.1998,"volume":1676},{"date":"2026-01-15","open":0.1808,"high":0.1978,"low":0.17,"close":0.1951,"adjusted_close":0.1951,"volume":16070},{"date":"2026-01-16","open":0.17,"high":0.17,"low":0.17,"close":0.17,"adjusted_close":0.17,"volume":226},{"date":"2026-01-20","open":0.16,"high":0.16,"low":0.16,"close":0.16,"adjusted_close":0.16,"volume":913},{"date":"2026-01-21","open":0.192,"high":0.2,"low":0.18,"close":0.18,"adjusted_close":0.18,"volume":8508},{"date":"2026-01-22","open":0.1801,"high":0.2,"low":0.17031,"close":0.17031,"adjusted_close":0.17031,"volume":2837},{"date":"2026-01-26","open":0.155,"high":0.155,"low":0.155,"close":0.155,"adjusted_close":0.155,"volume":241},{"date":"2026-01-29","open":0.15001,"high":0.15001,"low":0.15001,"close":0.15001,"adjusted_close":0.15001,"volume":325},{"date":"2026-02-02","open":0.1551,"high":0.2,"low":0.15,"close":0.2,"adjusted_close":0.2,"volume":6995},{"date":"2026-02-03","open":0.1808,"high":0.1808,"low":0.1808,"close":0.1808,"adjusted_close":0.1808,"volume":184},{"date":"2026-02-04","open":0.1515,"high":0.1799,"low":0.15,"close":0.15,"adjusted_close":0.15,"volume":7405},{"date":"2026-02-05","open":0.174901,"high":0.174901,"low":0.15,"close":0.1505,"adjusted_close":0.1505,"volume":23576},{"date":"2026-02-06","open":0.15,"high":0.1686,"low":0.15,"close":0.1686,"adjusted_close":0.1686,"volume":10514},{"date":"2026-02-11","open":0.1668,"high":0.1684,"low":0.1641,"close":0.1684,"adjusted_close":0.1684,"volume":3384},{"date":"2026-02-12","open":0.17,"high":0.2,"low":0.17,"close":0.189063,"adjusted_close":0.189063,"volume":17839},{"date":"2026-02-13","open":0.1998,"high":0.2,"low":0.1565,"close":0.1783,"adjusted_close":0.1783,"volume":23687},{"date":"2026-02-17","open":0.178,"high":0.28,"low":0.178,"close":0.25,"adjusted_close":0.25,"volume":36385},{"date":"2026-02-18","open":0.2,"high":0.25,"low":0.18,"close":0.199,"adjusted_close":0.199,"volume":31536},{"date":"2026-02-19","open":0.2,"high":0.25,"low":0.199901,"close":0.2499,"adjusted_close":0.2499,"volume":19862},{"date":"2026-02-25","open":0.184,"high":0.25,"low":0.15,"close":0.181,"adjusted_close":0.181,"volume":133707},{"date":"2026-02-26","open":0.2,"high":0.2,"low":0.2,"close":0.2,"adjusted_close":0.2,"volume":100},{"date":"2026-02-27","open":0.1998,"high":0.1999,"low":0.1998,"close":0.1999,"adjusted_close":0.1999,"volume":1065},{"date":"2026-03-02","open":0.2196,"high":0.2196,"low":0.2196,"close":0.2196,"adjusted_close":0.2196,"volume":1044},{"date":"2026-03-09","open":0.1833,"high":0.2281,"low":0.1833,"close":0.2281,"adjusted_close":0.2281,"volume":5380},{"date":"2026-03-10","open":0.165,"high":0.213,"low":0.165,"close":0.213,"adjusted_close":0.213,"volume":1151},{"date":"2026-03-11","open":0.18,"high":0.18,"low":0.1701,"close":0.1701,"adjusted_close":0.1701,"volume":219},{"date":"2026-03-16","open":0.2,"high":0.2,"low":0.1999,"close":0.2,"adjusted_close":0.2,"volume":24384},{"date":"2026-03-17","open":0.21,"high":0.2101,"low":0.21,"close":0.21,"adjusted_close":0.21,"volume":3266},{"date":"2026-03-18","open":0.18,"high":0.21,"low":0.18,"close":0.21,"adjusted_close":0.21,"volume":710},{"date":"2026-03-19","open":0.2,"high":0.21,"low":0.2,"close":0.21,"adjusted_close":0.21,"volume":608},{"date":"2026-03-20","open":0.15,"high":0.199899,"low":0.15,"close":0.153,"adjusted_close":0.153,"volume":2683},{"date":"2026-03-23","open":0.15,"high":0.17,"low":0.15,"close":0.17,"adjusted_close":0.17,"volume":6844},{"date":"2026-03-30","open":0.19,"high":0.19,"low":0.19,"close":0.19,"adjusted_close":0.19,"volume":114},{"date":"2026-04-02","open":0.2,"high":0.2,"low":0.1418,"close":0.2,"adjusted_close":0.2,"volume":8851},{"date":"2026-04-10","open":0.2,"high":0.2,"low":0.1489,"close":0.2,"adjusted_close":0.2,"volume":6381},{"date":"2026-04-16","open":0.2,"high":0.21,"low":0.2,"close":0.21,"adjusted_close":0.21,"volume":5170},{"date":"2026-04-29","open":0.22,"high":0.22,"low":0.205,"close":0.21,"adjusted_close":0.21,"volume":6586},{"date":"2026-05-01","open":0.21,"high":0.21,"low":0.21,"close":0.21,"adjusted_close":0.21,"volume":1282},{"date":"2026-05-08","open":0.2,"high":0.2,"low":0.2,"close":0.2,"adjusted_close":0.2,"volume":635},{"date":"2026-05-12","open":0.2,"high":0.2,"low":0.2,"close":0.2,"adjusted_close":0.2,"volume":2342},{"date":"2026-05-18","open":0.18,"high":0.195,"low":0.1201,"close":0.195,"adjusted_close":0.195,"volume":528},{"date":"2026-05-29","open":0.2,"high":0.21,"low":0.2,"close":0.21,"adjusted_close":0.21,"volume":3462},{"date":"2026-06-01","open":0.21,"high":0.21,"low":0.21,"close":0.21,"adjusted_close":0.21,"volume":2734},{"date":"2026-06-02","open":0.2,"high":0.2,"low":0.2,"close":0.2,"adjusted_close":0.2,"volume":2048},{"date":"2026-06-03","open":0.2,"high":0.2,"low":0.2,"close":0.2,"adjusted_close":0.2,"volume":1324},{"date":"2026-06-04","open":0.19,"high":0.19,"low":0.19,"close":0.19,"adjusted_close":0.19,"volume":8116},{"date":"2026-06-05","open":0.1294,"high":0.1647,"low":0.12,"close":0.1305,"adjusted_close":0.1305,"volume":2389},{"date":"2026-06-09","open":0.16,"high":0.16,"low":0.16,"close":0.16,"adjusted_close":0.16,"volume":100},{"date":"2026-06-10","open":0.17,"high":0.19,"low":0.17,"close":0.1767,"adjusted_close":0.1767,"volume":1929},{"date":"2026-06-11","open":0.2065,"high":0.2065,"low":0.2065,"close":0.2065,"adjusted_close":0.2065,"volume":319},{"date":"2026-06-12","open":0.1888,"high":0.19,"low":0.1201,"close":0.1201,"adjusted_close":0.1201,"volume":2162},{"date":"2026-06-15","open":0.1988,"high":0.1988,"low":0.18,"close":0.1918,"adjusted_close":0.1918,"volume":3629},{"date":"2026-06-17","open":0.2,"high":0.209899,"low":0.15,"close":0.15,"adjusted_close":0.15,"volume":3867},{"date":"2026-06-18","open":0.16001,"high":0.185,"low":0.16001,"close":0.185,"adjusted_close":0.185,"volume":1904}]}